braveox/Braveox.py
braveox/__init__.py
braveox/etc.py
braveox-1.2.5.dist-info/LICENSE
braveox-1.2.5.dist-info/METADATA
braveox-1.2.5.dist-info/WHEEL
braveox-1.2.5.dist-info/top_level.txt
braveox-1.2.5.dist-info/RECORD
