Metadata-Version: 2.1
Name: braveox
Version: 1.2.5
Summary: You can turn your number into a new type.
Home-page: https://space.bilibili.com/426222659
Author: Inn Ritsukenn
Author-email: ylx2005114514@163.com
Project-URL: Bug Tracker, https://github.com/pypa/sampleproject/issues
Classifier: Programming Language :: Python :: 3
Classifier: License :: OSI Approved :: MIT License
Classifier: Operating System :: OS Independent
Requires-Python: >=3.6
License-File: LICENSE
